oscar_docdata/__init__.py
oscar_docdata/appsettings.py
oscar_docdata/exceptions.py
oscar_docdata/facade.py
oscar_docdata/gateway.py
oscar_docdata/interface.py
oscar_docdata/managers.py
oscar_docdata/models.py
oscar_docdata/signals.py
oscar_docdata/urls.py
oscar_docdata/views.py
oscar_docdata/dashboard/__init__.py
oscar_docdata/dashboard/app.py
oscar_docdata/dashboard/forms.py
oscar_docdata/dashboard/views.py
oscar_docdata/locale/en/LC_MESSAGES/django.mo
oscar_docdata/locale/en/LC_MESSAGES/django.po
oscar_docdata/locale/nl/LC_MESSAGES/django.mo
oscar_docdata/locale/nl/LC_MESSAGES/django.po
oscar_docdata/management/__init__.py
oscar_docdata/management/commands/__init__.py
oscar_docdata/management/commands/docdata_report.py
oscar_docdata/management/commands/expire_docdata_orders.py
oscar_docdata/management/commands/update_docdata_order.py
oscar_docdata/migrations/0001_initial.py
oscar_docdata/migrations/0002_remove_directdebitpayment_and_polymorphic_ctype.py
oscar_docdata/migrations/__init__.py
oscar_docdata/templates/oscar_docdata/dashboard/orders/confirm_cancel.html
oscar_docdata/templates/oscar_docdata/dashboard/orders/detail.html
oscar_docdata/templates/oscar_docdata/dashboard/orders/list.html
django_oscar_docdata-1.3.3.dist-info/AUTHORS
django_oscar_docdata-1.3.3.dist-info/LICENSE
django_oscar_docdata-1.3.3.dist-info/LICENSE.rst
django_oscar_docdata-1.3.3.dist-info/METADATA
django_oscar_docdata-1.3.3.dist-info/WHEEL
django_oscar_docdata-1.3.3.dist-info/top_level.txt
django_oscar_docdata-1.3.3.dist-info/RECORD
