Metadata-Version: 2.1
Name: django-oscar-docdata
Version: 1.3.3
Summary: Docdata Payments Gateway integration for django-oscar
Home-page: https://github.com/django-oscar/django-oscar-docdata
Author: Diederik van der Boor
Author-email: opensource@edoburu.nl
License: Apache 2.0
Download-URL: https://github.com/django-oscar/django-oscar-docdata/zipball/master
Platform: UNKNOWN
Classifier: Development Status :: 4 - Beta
Classifier: Environment :: Web Environment
Classifier: Framework :: Django
Classifier: Intended Audience :: Developers
Classifier: License :: OSI Approved :: Apache Software License
Classifier: Operating System :: OS Independent
Classifier: Framework :: Django
Classifier: Framework :: Django :: 1.11
Classifier: Framework :: Django :: 2.0
Classifier: Framework :: Django :: 2.1
Classifier: Programming Language :: Python
Classifier: Programming Language :: Python :: 2.7
Classifier: Programming Language :: Python :: 3.5
Classifier: Programming Language :: Python :: 3.6
Classifier: Programming Language :: Python :: 3.7
Classifier: Topic :: Internet :: WWW/HTTP
Classifier: Topic :: Office/Business :: Financial
Classifier: Topic :: Software Development :: Libraries :: Python Modules
Requires-Dist: suds-jurko (>=0.6)
Requires-Dist: django-oscar (>=1.5)
Requires-Dist: six (>=1.10)
Provides-Extra: dev
Requires-Dist: wheel ; extra == 'dev'
Requires-Dist: twine ; extra == 'dev'
Requires-Dist: flake8 ; extra == 'dev'
Requires-Dist: pytest (<5) ; extra == 'dev'
Requires-Dist: pytest-django ; extra == 'dev'
Requires-Dist: pytest-mock ; extra == 'dev'
Requires-Dist: pytest-env ; extra == 'dev'
Requires-Dist: django-webtest ; extra == 'dev'
